README.md
__init__.py
downloader/__init__.py
downloader/extract_reanalysis.py
downloader/utils/__init__.py
downloader/utils/connection.py
poetry.lock
pyproject.toml
weather/__init__.py
weather/utils/__init__.py
weather/utils/episem.py
weather/utils/extract_coordinates.py
weather/utils/extract_latlons.py
weather/utils/globals.py
weather/utils/municipios.json
weather/utils/reanalysis_era5_single_levels.sql
weather/xr_extensions.py
satellite_copernicus-0.1.0.dist-info/WHEEL
satellite_copernicus-0.1.0.dist-info/METADATA
satellite_copernicus-0.1.0.dist-info/RECORD
